{
	"partitions" : [
		{
			"name" : "Top",
			"pins" : [
				{
					"name" : "pwm",
					"strict" : false
				},
				{
					"name" : "fil[0]",
					"strict" : false
				},
				{
					"name" : "fil[1]",
					"strict" : false
				},
				{
					"name" : "fil[2]",
					"strict" : false
				},
				{
					"name" : "fil[3]",
					"strict" : false
				},
				{
					"name" : "trigg",
					"strict" : false
				},
				{
					"name" : "LCD_EN",
					"strict" : false
				},
				{
					"name" : "LCD_RS",
					"strict" : false
				},
				{
					"name" : "LCD_DATA[0]",
					"strict" : false
				},
				{
					"name" : "LCD_DATA[1]",
					"strict" : false
				},
				{
					"name" : "LCD_DATA[2]",
					"strict" : false
				},
				{
					"name" : "LCD_DATA[3]",
					"strict" : false
				},
				{
					"name" : "LCD_DATA[4]",
					"strict" : false
				},
				{
					"name" : "LCD_DATA[5]",
					"strict" : false
				},
				{
					"name" : "LCD_DATA[6]",
					"strict" : false
				},
				{
					"name" : "LCD_DATA[7]",
					"strict" : false
				},
				{
					"name" : "SCL",
					"strict" : false
				},
				{
					"name" : "SDA",
					"strict" : false
				},
				{
					"name" : "clk",
					"strict" : false
				},
				{
					"name" : "_rst",
					"strict" : false
				},
				{
					"name" : "echo",
					"strict" : false
				},
				{
					"name" : "col[1]",
					"strict" : false
				},
				{
					"name" : "col[3]",
					"strict" : false
				},
				{
					"name" : "col[0]",
					"strict" : false
				},
				{
					"name" : "col[2]",
					"strict" : false
				}
			]
		}
	]
}